distortions/__init__.py
distortions/geometry/__init__.py
distortions/geometry/adjacency.py
distortions/geometry/affinity.py
distortions/geometry/geometry.py
distortions/geometry/laplacian.py
distortions/geometry/neighborhoods.py
distortions/geometry/rmetric.py
distortions/geometry/utils.py
distortions/visualization/README.md
distortions/visualization/__init__.py
distortions/visualization/eigenvalues.py
distortions/visualization/interactive.py
distortions/visualization/render.js
distortions/visualization/umap.py
distortions/visualization/widget/render.js
distortions-0.0.5.dist-info/METADATA
distortions-0.0.5.dist-info/WHEEL
distortions-0.0.5.dist-info/licenses/LICENSE
distortions-0.0.5.dist-info/RECORD
