Metadata-Version: 2.4
Name: distortions
Version: 0.0.5
Summary: Interactive visualization of distortion in nonlinear embeddings.
Project-URL: Homepage, https://github.com/krisrs1128/distortions/
Project-URL: Issues, https://github.com/krisrs1128/distortions/Issues/
Author-email: Kris Sankaran <ksankaran@wisc.edu>, Shuzhen Zhang <shuzhenz@uw.edu>, Chenab <chenab@uw.edu>, Marina Meila <mmp@uwaterloo.ca>
License: CC-BY-4.0
License-File: LICENSE
Classifier: License :: Other/Proprietary License
Classifier: Operating System :: OS Independent
Classifier: Programming Language :: Python :: 3
Requires-Python: >=3.8
Provides-Extra: plotting
Requires-Dist: altair; extra == 'plotting'
